Model/src/Util/register.v
`ifndef REGISTER
`define REGISTER

module register #(
    parameter WIDTH = 32
) (
    // Control Signal
    input  clk, en, rst,

    // Data Signal
    input  wire signed [WIDTH-1:0] in,
    output reg  signed [WIDTH-1:0] out
);
    always @(posedge clk) begin
        if (rst) begin
            out <= {WIDTH{1'b0}};
        end else if (en) begin
            out <= in;
        end
    end

endmodule
`endif

Model/src/Util/sigmoid.v
`ifndef SIGMOID
`define SIGMOID

// `include "register.v" // Use when only run this module
`include "Util/register.v" // Use to able run the neuron module

module sigmoid #(
    parameter WIDTH = 32,
    parameter FL = 24
) (
    input clk, en, rst,
    input signed [WIDTH-1:0] a,
    output signed [WIDTH-1:0] y
);
    
    // 1. Ambil tanda dan nilai absolut
    wire sign = a[WIDTH-1];
    wire signed [WIDTH-1:0] a_pos = (sign) ? (-a) : a;
    
    // 2. Koefisien untuk setiap segment
    reg signed [WIDTH-1:0] p1, p2, p3;
    
    // Threshold dalam Q8.24
    localparam signed [WIDTH-1:0] TH_15  = 32'h01800000; // 1.5
    localparam signed [WIDTH-1:0] TH_35  = 32'h03800000; // 3.5
    localparam signed [WIDTH-1:0] TH_60  = 32'h06000000; // 6.0
    
    reg [1:0] sel_p;

    always @(*) begin
        if (a_pos >= TH_60) begin          // a_pos >= 6.0
            sel_p = 2'b00;
        end else if (a_pos >= TH_35) begin // 3.5 <= a_pos < 6.0
            sel_p = 2'b01;
        end else if (a_pos >= TH_15) begin // 1.5 <= a_pos < 3.5
            sel_p = 2'b10;
        end else begin                     // 0.0 <= a_pos < 1.5
            sel_p = 2'b11;
        end
    end
    
    // 3. Hitung a_pos^2
    wire signed [WIDTH*2-1:0] a_sq_full = a * a;
    wire signed [WIDTH-1:0] a_sq = a_sq_full[FL+WIDTH-1:FL];
    
    // 4. Pipeline Stage 1 - Register Koefisien
    wire sign_reg;
    wire [1:0] sel_p_reg;
    wire signed [WIDTH-1:0] a_pos_reg, a_sq_reg;
    
    register #(.WIDTH(1)) reg_sign (.clk(clk), .en(en), .rst(rst), .in(sign), .out(sign_reg));
    register #(.WIDTH(2)) reg_sel_p (.clk(clk), .en(en), .rst(rst), .in(sel_p), .out(sel_p_reg));
    register #(.WIDTH(WIDTH)) reg_a_pos (.clk(clk), .en(en), .rst(rst), .in(a_pos), .out(a_pos_reg));
    register #(.WIDTH(WIDTH)) reg_a_sq (.clk(clk), .en(en), .rst(rst), .in(a_sq), .out(a_sq_reg));

    always @(*) begin
        case (sel_p_reg)
            2'b00  : begin
                p1 = 32'h00000000;  // 0
                p2 = 32'h00000000;  // 0
            end
            2'b01  : begin
                // -0.004609, 0.053606, 0.840844
                p1 = 32'hFFFED1F2;  // -0.004609
                p2 = 32'h000DB91F;  // 0.053606
            end
            2'b10  : begin
                // -0.029988, 0.223978, 0.551643
                p1 = 32'hFFF852B5;  // -0.029988
                p2 = 32'h0039569F;  // 0.223978
            end
            2'b11  : begin
                // -0.036623, 0.269097, 0.497822
                p1 = 32'hFFF69FE0;  // -0.036623
                p2 = 32'h0044E38A;  // 0.269097
            end
            default: begin
                p1 = 32'h00000000;  // 0
                p2 = 32'h00000000;  // 0
            end
        endcase
    end
    
    // 5. Multiply
    wire signed [WIDTH*2-1:0] term1_full = p1 * a_sq_reg;
    wire signed [WIDTH*2-1:0] term2_full = p2 * a_pos_reg;
    
    wire signed [WIDTH-1:0] term1 = term1_full[FL+WIDTH-1:FL];
    wire signed [WIDTH-1:0] term2 = term2_full[FL+WIDTH-1:FL];

    // PIPELINE STAGE 2
    wire sign_reg2;
    wire [1:0] sel_p_reg2;
    wire signed [WIDTH-1:0] term1_reg, term2_reg;

    register #(.WIDTH(1)) reg_sign2 (.clk(clk), .en(en), .rst(rst), .in(sign_reg), .out(sign_reg2));
    register #(.WIDTH(2)) reg_sel_p2 (.clk(clk), .en(en), .rst(rst), .in(sel_p_reg), .out(sel_p_reg2));
    register #(.WIDTH(WIDTH)) reg_term1 (.clk(clk), .en(en), .rst(rst), .in(term1), .out(term1_reg));
    register #(.WIDTH(WIDTH)) reg_term2 (.clk(clk), .en(en), .rst(rst), .in(term2), .out(term2_reg));

    always @(*) begin
        case (sel_p_reg2)
            2'b00  : begin
                p3 = 32'h01000000;  // 1.0 (untuk f(|x|))
            end
            2'b01  : begin
                // -0.004609, 0.053606, 0.840844
                p3 = 32'h00D7418D;  // 0.840844
            end
            2'b10  : begin
                // -0.029988, 0.223978, 0.551643
                p3 = 32'h008D387A;  // 0.551643
            end
            2'b11  : begin
                // -0.036623, 0.269097, 0.497822
                p3 = 32'h007F7143;  // 0.497822
            end
            default: begin
                p3 = 32'h01000000;  // 1.0 (untuk f(|x|))
            end
        endcase
    end
    
    // 6. Accumulate
    localparam signed [WIDTH-1:0] ONE = 32'h01000000;
    localparam signed [WIDTH-1:0] ZERO = 32'h00000000;
    
    wire signed [WIDTH-1:0] y_abs = term1_reg + term2_reg + p3;
    
    // Saturasi: 0 ≤ y_abs ≤ 1
    wire signed [WIDTH-1:0] y_abs_sat = 
        (y_abs > ONE) ? ONE : 
        (y_abs < ZERO) ? ZERO : y_abs;
    
    // Apply symmetry: f(-x) = 1 - f(x)
    wire signed [WIDTH-1:0] y_sigmoid_val = 
        (sign_reg2) ? (ONE - y_abs_sat) : y_abs_sat;
    
    // 7. Pipeline Stage 2 - Output
    register #(.WIDTH(WIDTH)) reg_out (.clk(clk), .en(en), .rst(rst), .in(y_sigmoid_val), .out(y));

endmodule
`endif

Model/src/Util/sigmoid_tb.v
`timescale 1ns / 1ps
`include "sigmoid.v"


module sigmoid_tb();

    // Parameters
    parameter WIDTH = 32;
    parameter FL = 24;

    // Signals
    reg clk;
    reg en;
    reg rst;
    reg signed [WIDTH-1:0] x; // Kita hubungkan ke port 'a' di modul
    wire signed [WIDTH-1:0] y;

    // Instansiasi Unit Under Test (UUT)
    sigmoid #(
        .WIDTH(WIDTH),
        .FL(FL)
    ) uut (
        .clk(clk),
        .en(en),
        .rst(rst),
        .a(x), // Port 'a' dihubungkan ke reg 'x'
        .y(y)
    );

    // Clock Generator (100 MHz)
    initial clk = 0;
    always #5 clk = ~clk;

    // Fungsi pembantu untuk menampilkan nilai Q8.24
    task display_q8_24;
        input signed [31:0] val;
        real r_val;
        begin
            r_val = $itor(val) / 16777216.0; // 2^24
            $write("%f (Hex: %h)", r_val, val);
        end
    endtask

    // Task untuk memberikan input dan menunggu pipeline (3-4 cycle)
    task test_value;
        input signed [31:0] val_in;
        begin
            x = val_in;
            @(posedge clk);
            // Menunggu 3 cycle agar data sampai ke output register
            repeat(3) @(posedge clk);
            $write("In: "); display_q8_24(val_in);
            $write(" | Out: "); display_q8_24(y);
            $display("");
        end
    endtask

    initial begin
        // Setup VCD
        $dumpfile("sigmoid_sim.vcd");
        $dumpvars(0, sigmoid_tb);

        // Initialize
        rst = 1;
        en = 0;
        x = 0;

        $display("------------------------------------------------------------");
        $display("Testing Pipelined Sigmoid Quadratic Implementation");
        $display("------------------------------------------------------------");

        #20;
        rst = 0;
        en = 1;
        @(posedge clk);

        // Test Case 1: x = -5
        test_value(32'hfb000000);

        // Test Case 2: x = -2.5 (Q24: 00800000)
        test_value(32'hfd800000);

        // Test Case 3: x = 0 (Q24: 02000000)
        test_value(32'h00000000);

        // Test Case 4: x = 2.5 (Q24: 04000000)
        test_value(32'h02800000);

        // Test Case 5: x = 5 (Saturasi 1.0)
        test_value(32'h05000000);


        $display("------------------------------------------------------------");
        $display("Simulasi Selesai. Cek file sigmoid_sim.vcd");
        $finish;
    end

endmodule

Model/src/Util/sigmoid_sim.vcd
$date
	Sat Jan 10 16:47:06 2026
$end
$version
	Icarus Verilog
$end
$timescale
	1ps
$end
$scope module sigmoid_tb $end
$var wire 32 ! y [31:0] $end
$var parameter 32 " FL $end
$var parameter 32 # WIDTH $end
$var reg 1 $ clk $end
$var reg 1 % en $end
$var reg 1 & rst $end
$var reg 32 ' x [31:0] $end
$scope module uut $end
$var wire 32 ( a [31:0] $end
$var wire 1 $ clk $end
$var wire 1 % en $end
$var wire 1 & rst $end
$var wire 32 ) y_sigmoid_val [31:0] $end
$var wire 32 * y_abs_sat [31:0] $end
$var wire 32 + y_abs [31:0] $end
$var wire 32 , y [31:0] $end
$var wire 32 - term2_reg [31:0] $end
$var wire 64 . term2_full [63:0] $end
$var wire 32 / term2 [31:0] $end
$var wire 32 0 term1_reg [31:0] $end
$var wire 64 1 term1_full [63:0] $end
$var wire 32 2 term1 [31:0] $end
$var wire 1 3 sign_reg2 $end
$var wire 1 4 sign_reg $end
$var wire 1 5 sign $end
$var wire 2 6 sel_p_reg2 [1:0] $end
$var wire 2 7 sel_p_reg [1:0] $end
$var wire 32 8 a_sq_reg [31:0] $end
$var wire 64 9 a_sq_full [63:0] $end
$var wire 32 : a_sq [31:0] $end
$var wire 32 ; a_pos_reg [31:0] $end
$var wire 32 < a_pos [31:0] $end
$var parameter 32 = FL $end
$var parameter 32 > ONE $end
$var parameter 32 ? TH_15 $end
$var parameter 32 @ TH_35 $end
$var parameter 32 A TH_60 $end
$var parameter 32 B WIDTH $end
$var parameter 32 C ZERO $end
$var reg 32 D p1 [31:0] $end
$var reg 32 E p2 [31:0] $end
$var reg 32 F p3 [31:0] $end
$var reg 2 G sel_p [1:0] $end
$scope module reg_a_pos $end
$var wire 1 $ clk $end
$var wire 1 % en $end
$var wire 32 H in [31:0] $end
$var wire 1 & rst $end
$var parameter 32 I WIDTH $end
$var reg 32 J out [31:0] $end
$upscope $end
$scope module reg_a_sq $end
$var wire 1 $ clk $end
$var wire 1 % en $end
$var wire 32 K in [31:0] $end
$var wire 1 & rst $end
$var parameter 32 L WIDTH $end
$var reg 32 M out [31:0] $end
$upscope $end
$scope module reg_out $end
$var wire 1 $ clk $end
$var wire 1 % en $end
$var wire 32 N in [31:0] $end
$var wire 1 & rst $end
$var parameter 32 O WIDTH $end
$var reg 32 P out [31:0] $end
$upscope $end
$scope module reg_sel_p $end
$var wire 1 $ clk $end
$var wire 1 % en $end
$var wire 2 Q in [1:0] $end
$var wire 1 & rst $end
$var parameter 32 R WIDTH $end
$var reg 2 S out [1:0] $end
$upscope $end
$scope module reg_sel_p2 $end
$var wire 1 $ clk $end
$var wire 1 % en $end
$var wire 2 T in [1:0] $end
$var wire 1 & rst $end
$var parameter 32 U WIDTH $end
$var reg 2 V out [1:0] $end
$upscope $end
$scope module reg_sign $end
$var wire 1 $ clk $end
$var wire 1 % en $end
$var wire 1 5 in $end
$var wire 1 & rst $end
$var parameter 32 W WIDTH $end
$var reg 1 4 out $end
$upscope $end
$scope module reg_sign2 $end
$var wire 1 $ clk $end
$var wire 1 % en $end
$var wire 1 4 in $end
$var wire 1 & rst $end
$var parameter 32 X WIDTH $end
$var reg 1 3 out $end
$upscope $end
$scope module reg_term1 $end
$var wire 1 $ clk $end
$var wire 1 % en $end
$var wire 32 Y in [31:0] $end
$var wire 1 & rst $end
$var parameter 32 Z WIDTH $end
$var reg 32 [ out [31:0] $end
$upscope $end
$scope module reg_term2 $end
$var wire 1 $ clk $end
$var wire 1 % en $end
$var wire 32 \ in [31:0] $end
$var wire 1 & rst $end
$var parameter 32 ] WIDTH $end
$var reg 32 ^ out [31:0] $end
$upscope $end
$upscope $end
$scope task display_q8_24 $end
$var reg 32 _ val [31:0] $end
$var real 1 ` r_val $end
$upscope $end
$scope task test_value $end
$var reg 32 a val_in [31:0] $end
$upscope $end
$upscope $end
$enddefinitions $end
$comment Show the parameter values. $end
$dumpall
b100000 ]
b100000 Z
b1 X
b1 W
b10 U
b10 R
b100000 O
b100000 L
b100000 I
b0 C
b100000 B
b110000000000000000000000000 A
b11100000000000000000000000 @
b1100000000000000000000000 ?
b1000000000000000000000000 >
b11000 =
b100000 #
b11000 "
$end
#0
$dumpvars
bx a
r0 `
bx _
bx ^
bx \
bx [
bx Y
bx V
bx T
bx S
b11 Q
bx P
bx N
bx M
b0 K
bx J
b0 H
b11 G
bx F
bx E
bx D
b0 <
bx ;
b0 :
b0 9
bx 8
bx 7
bx 6
05
x4
x3
bx 2
bx 1
bx 0
bx /
bx .
bx -
bx ,
bx +
bx *
bx )
b0 (
b0 '
1&
0%
0$
bx !
$end
#5000
b1000000000000000000000000 )
b1000000000000000000000000 N
b0 /
b0 \
b0 2
b0 Y
b1000000000000000000000000 *
b0 .
b0 E
b0 1
b0 D
b1000000000000000000000000 +
b1000000000000000000000000 F
04
b0 7
b0 S
b0 T
b0 ;
b0 J
b0 8
b0 M
03
b0 6
b0 V
b0 0
b0 [
b0 -
b0 ^
b0 !
b0 ,
b0 P
1$
#10000
0$
#15000
1$
#20000
0$
1%
0&
#25000
b10001001110001110001010 E
b11111111111101101001111111100000 D
b11 7
b11 S
b11 T
b1000000000000000000000000 !
b1000000000000000000000000 ,
b1000000000000000000000000 P
b1 G
b1 Q
15
b101000000000000000000000000 <
b101000000000000000000000000 H
b11001000000000000000000000000 :
b11001000000000000000000000000 K
b11001000000000000000000000000000000000000000000000000 9
b11111011000000000000000000000000 '
b11111011000000000000000000000000 (
b11111011000000000000000000000000 a
1$
#30000
0$
#35000
b11111110111000101000011 )
b11111110111000101000011 N
b11111110111000101000011 *
b11111110111000101000011 +
b11111110111000101000011 F
b11111111111000101000000010100010 2
b11111111111000101000000010100010 Y
b10001001001110110011011 /
b10001001001110110011011 \
b11011011100100011111 E
b11111111111111101101000111110010 D
b11 6
b11 V
b1111111111111111111000101000000010100010000000000000000000000000 1
b11001000000000000000000000000 8
b11001000000000000000000000000 M
b10001001001110110011011000000000000000000000000 .
b101000000000000000000000000 ;
b101000000000000000000000000 J
b1 7
b1 S
b1 T
14
1$
#40000
0$
#45000
b111111100101111111001010 *
b11010000000110110 )
b11010000000110110 N
b110101110100000110001101 F
13
b1 6
b1 V
b11111111111000101000000010100010 0
b11111111111000101000000010100010 [
b111111100101111111001010 +
b10001001001110110011011 -
b10001001001110110011011 ^
b11111110111000101000011 !
b11111110111000101000011 ,
b11111110111000101000011 P
1$
#50000
0$
#55000
b11010000000110110 !
b11010000000110110 ,
b11010000000110110 P
1$
#60000
0$
#65000
b10 G
b10 Q
b10100000000000000000000000 <
b10100000000000000000000000 H
b110010000000000000000000000 :
b110010000000000000000000000 K
b110010000000000000000000000000000000000000000000000 9
b11111101100000000000000000000000 '
b11111101100000000000000000000000 (
b11111101100000000000000000000000 a
r0.006350874900817871 `
b11010000000110110 _
1$
#70000
0$
#75000
b11111111110100000000010011101011 2
b11111111110100000000010011101011 Y
b100011110101100010001101 /
b100011110101100010001101 \
b1110010101011010011111 E
b11111111111110000101001010110101 D
b1111111111111111110100000000010011101011010000000000000000000000 1
b110010000000000000000000000 8
b110010000000000000000000000 M
b100011110101100010001101100000000000000000000000 .
b10100000000000000000000000 ;
b10100000000000000000000000 J
b10 7
b10 S
b10 T
1$
#80000
0$
#85000
b100110110101000001110 )
b100110110101000001110 N
b100011010011100001111010 F
b111011001001010111110010 *
b10 6
b10 V
b11111111110100000000010011101011 0
b11111111110100000000010011101011 [
b111011001001010111110010 +
b100011110101100010001101 -
b100011110101100010001101 ^
1$
#90000
0$
#95000
b100110110101000001110 !
b100110110101000001110 ,
b100110110101000001110 P
1$
#100000
0$
#105000
b11 G
b11 Q
05
b0 <
b0 H
b0 :
b0 K
b0 9
b0 '
b0 (
b0 a
r0.07583701610565186 `
b100110110101000001110 _
1$
#110000
0$
#115000
b0 2
b0 Y
b0 /
b0 \
b10001001110001110001010 E
b11111111111101101001111111100000 D
b0 1
b0 8
b0 M
b0 .
b0 ;
b0 J
b11 7
b11 S
b11 T
04
1$
#120000
0$
#125000
b11111110111000101000011 *
b11111110111000101000011 )
b11111110111000101000011 N
b11111110111000101000011 F
03
b11 6
b11 V
b0 0
b0 [
b11111110111000101000011 +
b0 -
b0 ^
1$
#130000
0$
#135000
b11111110111000101000011 !
b11111110111000101000011 ,
b11111110111000101000011 P
1$
#140000
0$
#145000
b10 G
b10 Q
b10100000000000000000000000 <
b10100000000000000000000000 H
b110010000000000000000000000 :
b110010000000000000000000000 K
b110010000000000000000000000000000000000000000000000 9
b10100000000000000000000000 '
b10100000000000000000000000 (
b10100000000000000000000000 a
r0.4978219866752625 `
b11111110111000101000011 _
1$
#150000
0$
#155000
b11111111110100000000010011101011 2
b11111111110100000000010011101011 Y
b100011110101100010001101 /
b100011110101100010001101 \
b1110010101011010011111 E
b11111111111110000101001010110101 D
b1111111111111111110100000000010011101011010000000000000000000000 1
b110010000000000000000000000 8
b110010000000000000000000000 M
b100011110101100010001101100000000000000000000000 .
b10100000000000000000000000 ;
b10100000000000000000000000 J
b10 7
b10 S
b10 T
1$
#160000
0$
#165000
b111011001001010111110010 )
b111011001001010111110010 N
b100011010011100001111010 F
b111011001001010111110010 *
b10 6
b10 V
b11111111110100000000010011101011 0
b11111111110100000000010011101011 [
b111011001001010111110010 +
b100011110101100010001101 -
b100011110101100010001101 ^
1$
#170000
0$
#175000
b111011001001010111110010 !
b111011001001010111110010 ,
b111011001001010111110010 P
1$
#180000
0$
#185000
b1 G
b1 Q
b101000000000000000000000000 <
b101000000000000000000000000 H
b11001000000000000000000000000 :
b11001000000000000000000000000 K
b11001000000000000000000000000000000000000000000000000 9
b101000000000000000000000000 '
b101000000000000000000000000 (
b101000000000000000000000000 a
r0.9241629838943481 `
b111011001001010111110010 _
1$
#190000
0$
#195000
b11111111111000101000000010100010 2
b11111111111000101000000010100010 Y
b10001001001110110011011 /
b10001001001110110011011 \
b11011011100100011111 E
b11111111111111101101000111110010 D
b1111111111111111111000101000000010100010000000000000000000000000 1
b11001000000000000000000000000 8
b11001000000000000000000000000 M
b10001001001110110011011000000000000000000000000 .
b101000000000000000000000000 ;
b101000000000000000000000000 J
b1 7
b1 S
b1 T
1$
#200000
0$
#205000
b111111100101111111001010 )
b111111100101111111001010 N
b111111100101111111001010 *
b110101110100000110001101 F
b1 6
b1 V
b11111111111000101000000010100010 0
b11111111111000101000000010100010 [
b111111100101111111001010 +
b10001001001110110011011 -
b10001001001110110011011 ^
1$
#210000
0$
#215000
b111111100101111111001010 !
b111111100101111111001010 ,
b111111100101111111001010 P
1$
#220000
0$
#225000
r0.9936491250991821 `
b111111100101111111001010 _
1$
